mco_agent/__init__.py
mco_agent/agent.py
mco_agent/config.py
mco_agent/dispatcher.py
mco_agent/exceptions.py
mco_agent/protocol.py
mco_agent/version.py
mco_agent/schemas/io.choria.mcorpc.external.v1.activation_reply.json
mco_agent/schemas/io.choria.mcorpc.external.v1.activation_request.json
mco_agent/schemas/io.choria.mcorpc.external.v1.rpc_reply.json
mco_agent/schemas/io.choria.mcorpc.external.v1.rpc_request.json
py_mco_agent-0.3.2.dist-info/LICENSE
py_mco_agent-0.3.2.dist-info/METADATA
py_mco_agent-0.3.2.dist-info/WHEEL
py_mco_agent-0.3.2.dist-info/top_level.txt
py_mco_agent-0.3.2.dist-info/RECORD
