Metadata-Version: 2.1
Name: py-mco-agent
Version: 0.3.2
Summary: A library for implementing Mcollecting agents in Python
Home-page: https://github.com/optiz0r/py-mco-agent
Author: Ben Roberts
Author-email: me@benroberts.net
License: UNKNOWN
Platform: UNKNOWN
Classifier: Programming Language :: Python :: 2
Classifier: Programming Language :: Python :: 3
Classifier: License :: OSI Approved :: Apache Software License
Classifier: Operating System :: OS Independent
Requires-Python: >=2.6
